baseobjects/__init__.py
baseobjects/bases/__init__.py
baseobjects/bases/basecallable.py
baseobjects/bases/basemeta.py
baseobjects/bases/baseobject.py
baseobjects/bases/collections/__init__.py
baseobjects/bases/collections/basedict.py
baseobjects/bases/collections/baselist.py
baseobjects/bases/sentinelobject.py
baseobjects/cachingtools/__init__.py
baseobjects/cachingtools/caches/__init__.py
baseobjects/cachingtools/caches/basetimedcache.py
baseobjects/cachingtools/caches/timedcache.py
baseobjects/cachingtools/caches/timedkeylesscache.py
baseobjects/cachingtools/caches/timedlrucache.py
baseobjects/cachingtools/caches/timedsinglecache.py
baseobjects/cachingtools/cachingobject.py
baseobjects/cachingtools/metaclasses/__init__.py
baseobjects/cachingtools/metaclasses/cachinginitmeta.py
baseobjects/cachingtools/metaclasses/cachingobjectmeta.py
baseobjects/collections/__init__.py
baseobjects/collections/circulardoublylinkedcontainer.py
baseobjects/collections/groupedlist.py
baseobjects/collections/orderabledict.py
baseobjects/collections/timeddict.py
baseobjects/composition/__init__.py
baseobjects/composition/basecomponent.py
baseobjects/composition/basecomposite.py
baseobjects/composition/basedispatchingcomposite.py
baseobjects/composition/dispatchablecomposite.py
baseobjects/dataclasses/__init__.py
baseobjects/dataclasses/parameters.py
baseobjects/functions/__init__.py
baseobjects/functions/basedecorator.py
baseobjects/functions/callablemultiplexer.py
baseobjects/functions/dynamiccallable.py
baseobjects/functions/functionregister.py
baseobjects/functions/methodregister.py
baseobjects/functions/singlekwargdispatch.py
baseobjects/header.py
baseobjects/metaclasses/__init__.py
baseobjects/metaclasses/initmeta.py
baseobjects/objects/__init__.py
baseobjects/objects/automaticproperties.py
baseobjects/objects/classnamespaceregister.py
baseobjects/objects/dispatchableclass.py
baseobjects/objects/registeredclass.py
baseobjects/operations/__init__.py
baseobjects-1.11.1.dist-info/LICENSE.rst
baseobjects-1.11.1.dist-info/METADATA
baseobjects-1.11.1.dist-info/WHEEL
baseobjects-1.11.1.dist-info/entry_points.txt
baseobjects-1.11.1.dist-info/RECORD
