Metadata-Version: 2.1
Name: baseobjects
Version: 1.11.1
Summary: Basic object templates.
Home-page: https://github.com/fongant/python-baseobjects
License: MIT
Author: Anthony Fong
Author-email: FongAnthonyM@gmail.com
Requires-Python: >=3.11,<4.0
Classifier: Development Status :: 4 - Beta
Classifier: License :: OSI Approved :: MIT License
Classifier: Programming Language :: Python :: 3
Classifier: Programming Language :: Python :: 3.11
Requires-Dist: bidict (>=0.22.0)
Requires-Dist: click (>=8.0.3)
Project-URL: Changelog, https://github.com/fongant/python-baseobjects/releases
Project-URL: Documentation, https://python-baseobjects.readthedocs.io
Project-URL: Repository, https://github.com/fongant/python-baseobjects
